qindus/__init__.py
qindus/data/loader.py
qindus/data/windows.py
qindus/pipelines/anomaly.py
qindus/quantum/backends.py
qindus/quantum/encoders.py
qindus/quantum/models.py
qindus/utils/metrics.py
qindus-0.1.1.dist-info/licenses/LICENSE.txt
qindus-0.1.1.dist-info/METADATA
qindus-0.1.1.dist-info/WHEEL
qindus-0.1.1.dist-info/top_level.txt
qindus-0.1.1.dist-info/RECORD
