Metadata-Version: 2.4
Name: qindus
Version: 0.1.1
Summary: Quantum-enhanced anomaly detection for industrial network traffic
Author: José Israel Nadal Vidal
Requires-Python: >=3.10
License-File: LICENSE.txt
Requires-Dist: numpy>=1.22
Requires-Dist: scapy>=2.5.0
Requires-Dist: qiskit>=1.0.0
Requires-Dist: qiskit-aer>=0.15.0
Dynamic: license-file
